GWXtreme/__init__.py
GWXtreme/bounded_2d_kde.py
GWXtreme/eos_model_selection.py
GWXtreme-0.3.0.dist-info/METADATA
GWXtreme-0.3.0.dist-info/WHEEL
GWXtreme-0.3.0.dist-info/top_level.txt
GWXtreme-0.3.0.dist-info/RECORD
