Metadata-Version: 2.1
Name: GWXtreme
Version: 0.3.0
Summary: Tools for inferences on extreme matter using gravitational wave parameter estimation data.
Home-page: https://github.com/shaonghosh/GWXtreme
Author: Shaon Ghosh
Author-email: shaon.ghosh@ligo.org
License: GPL-2+
Platform: UNKNOWN
Classifier: Development Status :: 3 - Alpha
Classifier: Environment :: Console
Classifier: Intended Audience :: Science/Research
Classifier: License :: OSI Approved :: GNU General Public License v2 or later (GPLv2+)
Classifier: Programming Language :: Python :: 3
Classifier: Programming Language :: Python :: 3.8
Classifier: Topic :: Scientific/Engineering :: Astronomy
Classifier: Topic :: Scientific/Engineering :: Physics
Requires-Dist: scipy
Requires-Dist: matplotlib
Requires-Dist: numpy
Requires-Dist: lalsuite
Requires-Dist: sphinx
Requires-Dist: ray
